[
    {
        "type":"1",
        "field":"prefix_string",
        "value":"ABC-",
        "entity":0,
        "autoload":"0"
     },
     {
        "type":"1",
        "field":"next_number",
        "value":"1",
        "entity":0,
        "autoload":"0"
     },
     {
        "type":"1",
        "field":"number_length",
        "value":"9",
        "entity":0,
        "autoload":"0"
     },
     {
      "type":"2",
      "field":"prefix_string",
      "value":"CG-",
      "entity":0,
      "autoload":"0"
   },
   {
      "type":"2",
      "field":"next_number",
      "value":"1",
      "entity":0,
      "autoload":"0"
   },
   {
      "type":"2",
      "field":"number_length",
      "value":"9",
      "entity":0,
      "autoload":"0"
   },
   {
      "type":"3",
      "field":"prefix_string",
      "value":"SP-",
      "entity":0,
      "autoload":"0"
   },
   {
      "type":"3",
      "field":"next_number",
      "value":"1",
      "entity":0,
      "autoload":"0"
   },
   {
      "type":"3",
      "field":"number_length",
      "value":"7",
      "entity":0,
      "autoload":"0"
   },
   {
      "type":"4",
      "field":"prefix_string",
      "value":"Test-",
      "entity":0,
      "autoload":"0"
   },
   {
      "type":"4",
      "field":"next_number",
      "value":"1",
      "entity":0,
      "autoload":"0"
   },
   {
      "type":"4",
      "field":"number_length",
      "value":"9",
      "entity":0,
      "autoload":"0"
   }
]